{
  "modules": [
    {
      "header": {
        "ID": "J1",
        "name": "Prismatic Joint",
        "date": "2022-09-15",
        "author": [
          "Jonathan K\u00fclz"
        ],
        "email": [
          "jonathan.kuelz@tum.de"
        ],
        "affiliation": [
          "Technical University of Munich"
        ],
        "cost": 0.0
      },
      "bodies": [
        {
          "ID": "J1_distal",
          "mass": 0.3377840421139745,
          "inertia": [
            [ 0.0012610604238921716, 0.0, 0.0 ],
            [ 0.0, 0.0012610604238921716, 0.0 ],
            [ 0.0, 0.0, 0.0002702272336911796 ]
          ],
          "r_com": [ 0.0, 0.0, 0.0 ],
          "connectors": [
            {
              "ID": "J1_distal",
              "pose": [
                [ 1.0, 0.0, 0.0, 0.0 ],
                [ 0.0, 1.0, 0.0, 0.0 ],
                [ 0.0, 0.0, 1.0, 0.08 ],
                [ 0.0, 0.0, 0.0, 1.0 ]
              ],
              "gender": "m",
              "type": "default",
              "size": [ 0.08 ]
            }
          ],
          "collision": [
            {
              "type": "cylinder",
              "parameters": {
                "r": 0.032,
                "z": 0.16
              },
              "pose": [
                [ 1.0, 0.0, 0.0, 0.0 ],
                [ 0.0, 1.0, 0.0, 0.0 ],
                [ 0.0, 0.0, 1.0, 0.0 ],
                [ 0.0, 0.0, 0.0, 1.0 ]
              ]
            }
          ]
        },
        {
          "ID": "J1_proximal",
          "mass": 0.26389378290154264,
          "inertia": [
            [ 0.0003848451000647497, 0.0, 0.0 ],
            [ 0.0, 0.0003848451000647497, 0.0 ],
            [ 0.0, 0.0, 0.0003298672286269283 ]
          ],
          "r_com": [ 0.0, 0.0, 0.0 ],
          "connectors": [
            {
              "ID": "J1_proximal",
              "pose": [
                [ 1.0, 0.0, 0.0, 0.0 ],
                [ 0.0, -1.0, -1.2246467991473532e-16, -6.123233995736766e-18 ],
                [ 0.0, 1.2246467991473532e-16, -1.0, -0.05 ],
                [ 0.0, 0.0, 0.0, 1.0 ]
              ],
              "gender": "f",
              "type": "default",
              "size": [ 0.08 ]
            }
          ],
          "collision": [
            {
              "type": "cylinder",
              "parameters": {
                "r": 0.04,
                "z": 0.1
              },
              "pose": [
                [ 1.0, 0.0, 0.0, 0.0 ],
                [ 0.0, 1.0, 0.0, 0.0 ],
                [ 0.0, 0.0, 1.0, 0.0 ],
                [ 0.0, 0.0, 0.0, 1.0 ]
              ]
            }
          ]
        }
      ],
      "joints": [
        {
          "ID": "Prismatic",
          "parent": "J1_proximal",
          "child": "J1_distal",
          "type": "prismatic",
          "passive": false,
          "poseParent": [
            [ 1.0, 0.0, 0.0, 0.0 ],
            [ 0.0, 1.0, 0.0, 0.0 ],
            [ 0.0, 0.0, 1.0, 0.05 ],
            [ 0.0, 0.0, 0.0, 1.0 ]
          ],
          "poseChild": [
            [ 1.0, 0.0, 0.0, 0.0 ],
            [ 0.0, 1.0, 0.0, 0.0 ],
            [ 0.0, 0.0, 1.0, 0.020000000000000004 ],
            [ 0.0, 0.0, 0.0, 1.0 ]
          ],
          "limits": {
            "positionLower": 0.0,
            "positionUpper": 0.06,
            "peakTorque": Infinity,
            "velocity": Infinity,
            "acceleration": Infinity
          },
          "gearRatio": 1.0,
          "motorInertia": 0.0,
          "frictionCoulomb": 0.0,
          "frictionViscous": 0.0
        }
      ]
    },
    {
      "header": {
        "ID": "J2",
        "name": "Revolute Joint",
        "date": "2022-09-15",
        "author": [
          "Jonathan K\u00fclz"
        ],
        "email": [
          "jonathan.kuelz@tum.de"
        ],
        "affiliation": [
          "Technical University of Munich"
        ],
        "cost": 0.0
      },
      "bodies": [
        {
          "ID": "J2_distal",
          "mass": 0.39584067435231396,
          "inertia": [
            [ 0.0009896016858807848, 0.0, 0.0 ],
            [ 0.0, 0.0009896016858807848, 0.0 ],
            [ 0.0, 0.0, 0.0004948008429403925 ]
          ],
          "r_com": [ 0.0, 0.0, 0.0 ],
          "connectors": [
            {
              "ID": "J2_distal",
              "pose": [
                [ 1.0, 0.0, 0.0, 0.0 ],
                [ 0.0, 1.0, 0.0, 0.0 ],
                [ 0.0, 0.0, 1.0, 0.075 ],
                [ 0.0, 0.0, 0.0, 1.0 ]
              ],
              "gender": "m",
              "type": "default",
              "size": [ 0.08 ]
            }
          ],
          "collision": [
            {
              "type": "cylinder",
              "parameters": {
                "r": 0.04,
                "z": 0.15
              },
              "pose": [
                [ 1.0, 0.0, 0.0, 0.0 ],
                [ 0.0, 1.0, 0.0, 0.0 ],
                [ 0.0, 0.0, 1.0, 0.0 ],
                [ 0.0, 0.0, 0.0, 1.0 ]
              ]
            }
          ]
        },
        {
          "ID": "J2_proximal",
          "mass": 0.39584067435231396,
          "inertia": [
            [ 0.0009896016858807848, 0.0, 0.0 ],
            [ 0.0, 0.0009896016858807848, 0.0 ],
            [ 0.0, 0.0, 0.0004948008429403925 ]
          ],
          "r_com": [ 0.0, 0.0, 0.0 ],
          "connectors": [
            {
              "ID": "J2_proximal",
              "pose": [
                [ 1.0, 0.0, 0.0, 0.0 ],
                [ 0.0, -1.0, -1.2246467991473532e-16, -9.184850993605149e-18 ],
                [ 0.0, 1.2246467991473532e-16, -1.0, -0.075 ],
                [ 0.0, 0.0, 0.0, 1.0 ]
              ],
              "gender": "f",
              "type": "default",
              "size": [ 0.08 ]
            }
          ],
          "collision": [
            {
              "type": "cylinder",
              "parameters": {
                "r": 0.04,
                "z": 0.15
              },
              "pose": [
                [ 1.0, 0.0, 0.0, 0.0 ],
                [ 0.0, 1.0, 0.0, 0.0 ],
                [ 0.0, 0.0, 1.0, 0.0 ],
                [ 0.0, 0.0, 0.0, 1.0 ]
              ]
            },
            {
              "type": "sphere",
              "parameters": {
                "r": 0.04
              },
              "pose": [
                [ 1.0, 0.0, 0.0, 0.0 ],
                [ 0.0, 1.0, 0.0, 0.0 ],
                [ 0.0, 0.0, 1.0, 0.075 ],
                [ 0.0, 0.0, 0.0, 1.0 ]
              ]
            }
          ]
        }
      ],
      "joints": [
        {
          "ID": "Revolute",
          "parent": "J2_proximal",
          "child": "J2_distal",
          "type": "revolute",
          "passive": false,
          "poseParent": [
            [ 6.123233995736766e-17, 0.0, 1.0, 0.0 ],
            [ 0.0, 1.0, 0.0, 0.0 ],
            [ -1.0, 0.0, 6.123233995736766e-17, 0.075 ],
            [ 0.0, 0.0, 0.0, 1.0 ]
          ],
          "poseChild": [
            [ 1.0, 0.0, 0.0, 0.0 ],
            [ 0.0, 1.0, 0.0, 0.0 ],
            [ 0.0, 0.0, 1.0, 0.075 ],
            [ 0.0, 0.0, 0.0, 1.0 ]
          ],
          "limits": {
            "positionLower": -3.141592653589793,
            "positionUpper": 3.141592653589793,
            "peakTorque": 1000.0,
            "velocity": 10.0,
            "acceleration": Infinity
          },
          "gearRatio": 1.0,
          "motorInertia": 0.0,
          "frictionCoulomb": 0.0,
          "frictionViscous": 0.0
        }
      ]
    },
    {
      "header": {
        "ID": "base",
        "name": "Base",
        "date": "2022-09-15",
        "author": [
          "Jonathan K\u00fclz"
        ],
        "email": [
          "jonathan.kuelz@tum.de"
        ],
        "affiliation": [
          "Technical University of Munich"
        ],
        "cost": 0.0
      },
      "bodies": [
        {
          "ID": "base",
          "mass": 0.0,
          "inertia": [
            [ 0.0, 0.0, 0.0 ],
            [ 0.0, 0.0, 0.0 ],
            [ 0.0, 0.0, 0.0 ]
          ],
          "r_com": [ 0.0, 0.0, 0.0 ],
          "connectors": [
            {
              "ID": "base",
              "pose": [
                [ 1.0, 0.0, 0.0, 0.0 ],
                [ 0.0, -1.0, -1.2246467991473532e-16, 0.0 ],
                [ 0.0, 1.2246467991473532e-16, -1.0, 0.0 ],
                [ 0.0, 0.0, 0.0, 1.0 ]
              ],
              "gender": "f",
              "type": "base",
              "size": [ 0.08 ]
            },
            {
              "ID": "base2robot",
              "pose": [
                [ -6.123233995736766e-17, -7.498798913309288e-33, 1.0, 0.05 ],
                [ 1.2246467991473532e-16, -1.0, 0.0, 0.0 ],
                [ 1.0, 1.2246467991473532e-16, 6.123233995736766e-17, 0.05 ],
                [ 0.0, 0.0, 0.0, 1.0 ]
              ],
              "gender": "m",
              "type": "default",
              "size": [ 0.08 ]
            }
          ],
          "collision": [
            {
              "type": "box",
              "parameters": {
                "x": 0.1,
                "y": 0.1,
                "z": 0.1
              },
              "pose": [
                [ 1.0, 0.0, 0.0, 0.0 ],
                [ 0.0, 1.0, 0.0, 0.0 ],
                [ 0.0, 0.0, 1.0, 0.05 ],
                [ 0.0, 0.0, 0.0, 1.0 ]
              ]
            }
          ]
        }
      ],
      "joints": []
    },
    {
      "header": {
        "ID": "eef",
        "name": "Demo EEF",
        "date": "2022-09-15",
        "author": [
          "Jonathan K\u00fclz"
        ],
        "email": [
          "jonathan.kuelz@tum.de"
        ],
        "affiliation": [
          "Technical University of Munich"
        ],
        "cost": 0.0
      },
      "bodies": [
        {
          "ID": "EEF",
          "mass": 0.0,
          "inertia": [
            [ 0.0, 0.0, 0.0 ],
            [ 0.0, 0.0, 0.0 ],
            [ 0.0, 0.0, 0.0 ]
          ],
          "r_com": [ 0.0, 0.0, 0.0 ],
          "connectors": [
            {
              "ID": "end-effector",
              "pose": [
                [ 1.0, 0.0, 0.0, 0.0 ],
                [ 0.0, 1.0, 0.0, 0.0 ],
                [ 0.0, 0.0, 1.0, 0.04 ],
                [ 0.0, 0.0, 0.0, 1.0 ]
              ],
              "gender": "m",
              "type": "eef",
              "size": []
            },
            {
              "ID": "robot2eef",
              "pose": [
                [ 1.0, 0.0, 0.0, 0.0 ],
                [ 0.0, -1.0, -1.2246467991473532e-16, 0.0 ],
                [ 0.0, 1.2246467991473532e-16, -1.0, 0.0 ],
                [ 0.0, 0.0, 0.0, 1.0 ]
              ],
              "gender": "f",
              "type": "default",
              "size": [ 0.08 ]
            }
          ],
          "collision": [
            {
              "type": "sphere",
              "parameters": {
                "r": 0.016
              },
              "pose": [
                [ 1.0, 0.0, 0.0, 0.0 ],
                [ 0.0, 1.0, 0.0, 0.0 ],
                [ 0.0, 0.0, 1.0, 0.04 ],
                [ 0.0, 0.0, 0.0, 1.0 ]
              ]
            }
          ]
        }
      ],
      "joints": []
    },
    {
      "header": {
        "ID": "i_15",
        "name": "I shaped link 0.08-0.08-15",
        "date": "2022-09-15",
        "author": [
          "Jonathan K\u00fclz"
        ],
        "email": [
          "jonathan.kuelz@tum.de"
        ],
        "affiliation": [
          "Technical University of Munich"
        ],
        "cost": 0.0
      },
      "bodies": [
        {
          "ID": "i_15",
          "mass": 0.39584067435231396,
          "inertia": [
            [ 0.0009896016858807848, 0.0, 0.0 ],
            [ 0.0, 0.0009896016858807848, 0.0 ],
            [ 0.0, 0.0, 0.0004948008429403925 ]
          ],
          "r_com": [ 0.0, 0.0, 0.0 ],
          "connectors": [
            {
              "ID": "8-0",
              "pose": [
                [ 1.0, 0.0, 0.0, 0.0 ],
                [ 0.0, -1.0, -1.2246467991473532e-16, -9.184850993605149e-18 ],
                [ 0.0, 1.2246467991473532e-16, -1.0, -0.075 ],
                [ 0.0, 0.0, 0.0, 1.0 ]
              ],
              "gender": "f",
              "type": "default",
              "size": [ 0.08 ]
            },
            {
              "ID": "8-1",
              "pose": [
                [ 1.0, 0.0, 0.0, 0.0 ],
                [ 0.0, 1.0, 0.0, 0.0 ],
                [ 0.0, 0.0, 1.0, 0.075 ],
                [ 0.0, 0.0, 0.0, 1.0 ]
              ],
              "gender": "m",
              "type": "default",
              "size": [ 0.08 ]
            }
          ],
          "collision": [
            {
              "type": "cylinder",
              "parameters": {
                "r": 0.04,
                "z": 0.15
              },
              "pose": [
                [ 1.0, 0.0, 0.0, 0.0 ],
                [ 0.0, 1.0, 0.0, 0.0 ],
                [ 0.0, 0.0, 1.0, 0.0 ],
                [ 0.0, 0.0, 0.0, 1.0 ]
              ]
            }
          ]
        }
      ],
      "joints": []
    },
    {
      "header": {
        "ID": "i_30",
        "name": "I shaped link 0.08-0.08-30",
        "date": "2022-09-15",
        "author": [
          "Jonathan K\u00fclz"
        ],
        "email": [
          "jonathan.kuelz@tum.de"
        ],
        "affiliation": [
          "Technical University of Munich"
        ],
        "cost": 0.0
      },
      "bodies": [
        {
          "ID": "i_30",
          "mass": 0.7916813487046279,
          "inertia": [
            [ 0.006432410958225102, 0.0, 0.0 ],
            [ 0.0, 0.006432410958225102, 0.0 ],
            [ 0.0, 0.0, 0.000989601685880785 ]
          ],
          "r_com": [ 0.0, 0.0, 0.0 ],
          "connectors": [
            {
              "ID": "8-0",
              "pose": [
                [ 1.0, 0.0, 0.0, 0.0 ],
                [ 0.0, -1.0, -1.2246467991473532e-16, -1.8369701987210297e-17 ],
                [ 0.0, 1.2246467991473532e-16, -1.0, -0.15 ],
                [ 0.0, 0.0, 0.0, 1.0 ]
              ],
              "gender": "f",
              "type": "default",
              "size": [ 0.08 ]
            },
            {
              "ID": "8-1",
              "pose": [
                [ 1.0, 0.0, 0.0, 0.0 ],
                [ 0.0, 1.0, 0.0, 0.0 ],
                [ 0.0, 0.0, 1.0, 0.15 ],
                [ 0.0, 0.0, 0.0, 1.0 ]
              ],
              "gender": "m",
              "type": "default",
              "size": [ 0.08 ]
            }
          ],
          "collision": [
            {
              "type": "cylinder",
              "parameters": {
                "r": 0.04,
                "z": 0.3
              },
              "pose": [
                [ 1.0, 0.0, 0.0, 0.0 ],
                [ 0.0, 1.0, 0.0, 0.0 ],
                [ 0.0, 0.0, 1.0, 0.0 ],
                [ 0.0, 0.0, 0.0, 1.0 ]
              ]
            }
          ]
        }
      ],
      "joints": []
    },
    {
      "header": {
        "ID": "i_45",
        "name": "I shaped link 0.08-0.08-45",
        "date": "2022-09-15",
        "author": [
          "Jonathan K\u00fclz"
        ],
        "email": [
          "jonathan.kuelz@tum.de"
        ],
        "affiliation": [
          "Technical University of Munich"
        ],
        "cost": 0.0
      },
      "bodies": [
        {
          "ID": "i_45",
          "mass": 1.1875220230569419,
          "inertia": [
            [ 0.020781635403496486, 0.0, 0.0 ],
            [ 0.0, 0.020781635403496486, 0.0 ],
            [ 0.0, 0.0, 0.0014844025288211773 ]
          ],
          "r_com": [ 0.0, 0.0, 0.0 ],
          "connectors": [
            {
              "ID": "8-0",
              "pose": [
                [ 1.0, 0.0, 0.0, 0.0 ],
                [ 0.0, -1.0, -1.2246467991473532e-16, -2.7554552980815448e-17 ],
                [ 0.0, 1.2246467991473532e-16, -1.0, -0.225 ],
                [ 0.0, 0.0, 0.0, 1.0 ]
              ],
              "gender": "f",
              "type": "default",
              "size": [ 0.08 ]
            },
            {
              "ID": "8-1",
              "pose": [
                [ 1.0, 0.0, 0.0, 0.0 ],
                [ 0.0, 1.0, 0.0, 0.0 ],
                [ 0.0, 0.0, 1.0, 0.225 ],
                [ 0.0, 0.0, 0.0, 1.0 ]
              ],
              "gender": "m",
              "type": "default",
              "size": [ 0.08 ]
            }
          ],
          "collision": [
            {
              "type": "cylinder",
              "parameters": {
                "r": 0.04,
                "z": 0.45
              },
              "pose": [
                [ 1.0, 0.0, 0.0, 0.0 ],
                [ 0.0, 1.0, 0.0, 0.0 ],
                [ 0.0, 0.0, 1.0, 0.0 ],
                [ 0.0, 0.0, 0.0, 1.0 ]
              ]
            }
          ]
        }
      ],
      "joints": []
    },
    {
      "header": {
        "ID": "l_15",
        "name": "L shaped link 0.1-0.08-15",
        "date": "2022-09-15",
        "author": [
          "Jonathan K\u00fclz"
        ],
        "email": [
          "jonathan.kuelz@tum.de"
        ],
        "affiliation": [
          "Technical University of Munich"
        ],
        "cost": 0.0
      },
      "bodies": [
        {
          "ID": "l_15",
          "mass": 0.6597344572538566,
          "inertia": [
            [ 0.0012754866173574563, 0.0, -0.0005937610115284712 ],
            [ 0.0, 0.0026609289775905553, 0.0 ],
            [ -0.0005937610115284712, 0.0, 0.0022101104318004196 ]
          ],
          "r_com": [ 0.045, 0.0, 0.08000000000000002 ],
          "connectors": [
            {
              "ID": "8-0",
              "pose": [
                [ 1.0, 0.0, 0.0, 0.0 ],
                [ 0.0, -1.0, -1.2246467991473532e-16, 0.0 ],
                [ 0.0, 1.2246467991473532e-16, -1.0, 0.0 ],
                [ 0.0, 0.0, 0.0, 1.0 ]
              ],
              "gender": "f",
              "type": "default",
              "size": [ 0.08 ]
            },
            {
              "ID": "8-1",
              "pose": [
                [ 6.123233995736766e-17, 0.0, 1.0, 0.15 ],
                [ 0.0, 1.0, 0.0, 0.0 ],
                [ -1.0, 0.0, 6.123233995736766e-17, 0.10000000000000002 ],
                [ 0.0, 0.0, 0.0, 1.0 ]
              ],
              "gender": "m",
              "type": "default",
              "size": [ 0.08 ]
            }
          ],
          "collision": [
            {
              "type": "cylinder",
              "parameters": {
                "r": 0.04,
                "z": 0.1
              },
              "pose": [
                [ 1.0, 0.0, 0.0, 0.0 ],
                [ 0.0, 1.0, 0.0, 0.0 ],
                [ 0.0, 0.0, 1.0, 0.05 ],
                [ 0.0, 0.0, 0.0, 1.0 ]
              ]
            },
            {
              "type": "cylinder",
              "parameters": {
                "r": 0.04,
                "z": 0.15
              },
              "pose": [
                [ 6.123233995736766e-17, 0.0, 1.0, 0.075 ],
                [ 0.0, 1.0, 0.0, 0.0 ],
                [ -1.0, 0.0, 6.123233995736766e-17, 0.10000000000000002 ],
                [ 0.0, 0.0, 0.0, 1.0 ]
              ]
            },
            {
              "type": "sphere",
              "parameters": {
                "r": 0.04
              },
              "pose": [
                [ 1.0, 0.0, 0.0, 0.0 ],
                [ 0.0, 1.0, 0.0, 0.0 ],
                [ 0.0, 0.0, 1.0, 0.1 ],
                [ 0.0, 0.0, 0.0, 1.0 ]
              ]
            }
          ]
        }
      ],
      "joints": []
    },
    {
      "header": {
        "ID": "l_30",
        "name": "L shaped link 0.1-0.08-30",
        "date": "2022-09-15",
        "author": [
          "Jonathan K\u00fclz"
        ],
        "email": [
          "jonathan.kuelz@tum.de"
        ],
        "affiliation": [
          "Technical University of Munich"
        ],
        "cost": 0.0
      },
      "bodies": [
        {
          "ID": "l_30",
          "mass": 1.0555751316061706,
          "inertia": [
            [ 0.0018692476288859272, 0.0, -0.0014844025288211777 ],
            [ 0.0, 0.011765264487693777, 0.0 ],
            [ -0.0014844025288211777, 0.0, 0.011215485773315562 ]
          ],
          "r_com": [ 0.1125, 0.0, 0.08750000000000002 ],
          "connectors": [
            {
              "ID": "8-0",
              "pose": [
                [ 1.0, 0.0, 0.0, 0.0 ],
                [ 0.0, -1.0, -1.2246467991473532e-16, 0.0 ],
                [ 0.0, 1.2246467991473532e-16, -1.0, 0.0 ],
                [ 0.0, 0.0, 0.0, 1.0 ]
              ],
              "gender": "f",
              "type": "default",
              "size": [ 0.08 ]
            },
            {
              "ID": "8-1",
              "pose": [
                [ 6.123233995736766e-17, 0.0, 1.0, 0.3 ],
                [ 0.0, 1.0, 0.0, 0.0 ],
                [ -1.0, 0.0, 6.123233995736766e-17, 0.10000000000000002 ],
                [ 0.0, 0.0, 0.0, 1.0 ]
              ],
              "gender": "m",
              "type": "default",
              "size": [ 0.08 ]
            }
          ],
          "collision": [
            {
              "type": "cylinder",
              "parameters": {
                "r": 0.04,
                "z": 0.1
              },
              "pose": [
                [ 1.0, 0.0, 0.0, 0.0 ],
                [ 0.0, 1.0, 0.0, 0.0 ],
                [ 0.0, 0.0, 1.0, 0.05 ],
                [ 0.0, 0.0, 0.0, 1.0 ]
              ]
            },
            {
              "type": "cylinder",
              "parameters": {
                "r": 0.04,
                "z": 0.3
              },
              "pose": [
                [ 6.123233995736766e-17, 0.0, 1.0, 0.15 ],
                [ 0.0, 1.0, 0.0, 0.0 ],
                [ -1.0, 0.0, 6.123233995736766e-17, 0.1 ],
                [ 0.0, 0.0, 0.0, 1.0 ]
              ]
            },
            {
              "type": "sphere",
              "parameters": {
                "r": 0.04
              },
              "pose": [
                [ 1.0, 0.0, 0.0, 0.0 ],
                [ 0.0, 1.0, 0.0, 0.0 ],
                [ 0.0, 0.0, 1.0, 0.1 ],
                [ 0.0, 0.0, 0.0, 1.0 ]
              ]
            }
          ]
        }
      ],
      "joints": []
    },
    {
      "header": {
        "ID": "l_45",
        "name": "L shaped link 0.1-0.08-45",
        "date": "2022-09-15",
        "author": [
          "Jonathan K\u00fclz"
        ],
        "email": [
          "jonathan.kuelz@tum.de"
        ],
        "affiliation": [
          "Technical University of Munich"
        ],
        "cost": 0.0
      },
      "bodies": [
        {
          "ID": "l_45",
          "mass": 1.4514158059584845,
          "inertia": [
            [ 0.0024090303666390827, 0.0, -0.002429022319889201 ],
            [ 0.0, 0.03263686368081579, 0.0 ],
            [ -0.002429022319889201, 0.0, 0.032042103071624806 ]
          ],
          "r_com": [ 0.1840909090909091, 0.0, 0.09090909090909093 ],
          "connectors": [
            {
              "ID": "8-0",
              "pose": [
                [ 1.0, 0.0, 0.0, 0.0 ],
                [ 0.0, -1.0, -1.2246467991473532e-16, 0.0 ],
                [ 0.0, 1.2246467991473532e-16, -1.0, 0.0 ],
                [ 0.0, 0.0, 0.0, 1.0 ]
              ],
              "gender": "f",
              "type": "default",
              "size": [ 0.08 ]
            },
            {
              "ID": "8-1",
              "pose": [
                [ 6.123233995736766e-17, 0.0, 1.0, 0.45 ],
                [ 0.0, 1.0, 0.0, 0.0 ],
                [ -1.0, 0.0, 6.123233995736766e-17, 0.10000000000000003 ],
                [ 0.0, 0.0, 0.0, 1.0 ]
              ],
              "gender": "m",
              "type": "default",
              "size": [ 0.08 ]
            }
          ],
          "collision": [
            {
              "type": "cylinder",
              "parameters": {
                "r": 0.04,
                "z": 0.1
              },
              "pose": [
                [ 1.0, 0.0, 0.0, 0.0 ],
                [ 0.0, 1.0, 0.0, 0.0 ],
                [ 0.0, 0.0, 1.0, 0.05 ],
                [ 0.0, 0.0, 0.0, 1.0 ]
              ]
            },
            {
              "type": "cylinder",
              "parameters": {
                "r": 0.04,
                "z": 0.45
              },
              "pose": [
                [ 6.123233995736766e-17, 0.0, 1.0, 0.225 ],
                [ 0.0, 1.0, 0.0, 0.0 ],
                [ -1.0, 0.0, 6.123233995736766e-17, 0.10000000000000002 ],
                [ 0.0, 0.0, 0.0, 1.0 ]
              ]
            },
            {
              "type": "sphere",
              "parameters": {
                "r": 0.04
              },
              "pose": [
                [ 1.0, 0.0, 0.0, 0.0 ],
                [ 0.0, 1.0, 0.0, 0.0 ],
                [ 0.0, 0.0, 1.0, 0.1 ],
                [ 0.0, 0.0, 0.0, 1.0 ]
              ]
            }
          ]
        }
      ],
      "joints": []
    }
  ]
}